setup.cfg
setup.py
src/github/__init__.py
src/github/issues.py
src/github/utils.py
src/github/version.py
src/github_cli.egg-info/PKG-INFO
src/github_cli.egg-info/SOURCES.txt
src/github_cli.egg-info/dependency_links.txt
src/github_cli.egg-info/entry_points.txt
src/github_cli.egg-info/requires.txt
src/github_cli.egg-info/top_level.txt