Metadata-Version: 1.0
Name: github-cli
Version: 1.0.0
Summary: A command-line interface to the GitHub Issues API v2.
Home-page: http://packages.python.org/github-cli
Author: Sander Smits
Author-email: jhmsmits@gmail.com
License: BSD
Platform: UNKNOWN
Classifier: Development Status :: 4 - Beta
Classifier: Environment :: Console
Classifier: Intended Audience :: Developers
Classifier: Intended Audience :: System Administrators
Classifier: License :: OSI Approved :: BSD License
Classifier: Operating System :: MacOS :: MacOS X
Classifier: Operating System :: Unix
Classifier: Operating System :: POSIX
Classifier: Programming Language :: Python
Classifier: Topic :: Software Development :: Bug Tracking
